itk_cucim/__init__.py
itk_cucim-0.0.2.dist-info/LICENSE
itk_cucim-0.0.2.dist-info/WHEEL
itk_cucim-0.0.2.dist-info/METADATA
itk_cucim-0.0.2.dist-info/RECORD
